piezo/__init__.py
piezo/catalogue.py
piezo/grammar_GARC1.py
piezo/py.typed
piezo-0.9.1.data/scripts/piezo-predict.py
piezo-0.9.1.dist-info/LICENSE
piezo-0.9.1.dist-info/METADATA
piezo-0.9.1.dist-info/WHEEL
piezo-0.9.1.dist-info/top_level.txt
piezo-0.9.1.dist-info/RECORD
