Metadata-Version: 2.2
Name: piezo
Version: 0.9.1
Summary: Predicting the effect of an antibiotic from gene mutations
Home-page: https://github.com/oxfordmmm/piezo
Author: Philip W Fowler
Author-email: philip.fowler@ndm.ox.ac.uk
License: University of Oxford, see LICENSE.md
Classifier: Intended Audience :: Science/Research
Classifier: Programming Language :: Python :: 3
Classifier: License :: OSI Approved :: MIT License
Classifier: Operating System :: OS Independent
Requires-Python: >=3.10
License-File: LICENSE
Requires-Dist: pandas
Requires-Dist: ujson
Requires-Dist: pytest
Requires-Dist: pytest-cov
